absnjw456tbh-0.1.0.dist-info/licenses/LICENSE
own_package/__init__.py
own_package/core.py
absnjw456tbh-0.1.0.dist-info/METADATA
absnjw456tbh-0.1.0.dist-info/WHEEL
absnjw456tbh-0.1.0.dist-info/top_level.txt
absnjw456tbh-0.1.0.dist-info/RECORD
