Metadata-Version: 2.4
Name: absnjw456tbh
Version: 0.1.0
Summary: A small utility for string operations
Home-page: https://github.com/dianapps233lokesh/own_package
Author: Lokesh Kumar Saini
Author-email: lokesh.saini@dianapps.com
Requires-Python: >=3.6
License-File: LICENSE
Dynamic: author
Dynamic: author-email
Dynamic: home-page
Dynamic: license-file
Dynamic: requires-python
Dynamic: summary
